baml_agents/__init__.py
baml_agents/_agent_tools/__init__.py
baml_agents/_agent_tools/_action.py
baml_agents/_agent_tools/_baml_client_passthrough_wrapper.py
baml_agents/_agent_tools/_mcp.py
baml_agents/_agent_tools/_mcp_tool_to_json_schema.py
baml_agents/_agent_tools/_str_result.py
baml_agents/_agent_tools/_tool_definition.py
baml_agents/_agent_tools/_json_schema_to_baml_source/__init__.py
baml_agents/_agent_tools/_json_schema_to_baml_source/_default_callbacks.py
baml_agents/_agent_tools/_json_schema_to_baml_source/_facade.py
baml_agents/_agent_tools/_json_schema_to_baml_source/_interfaces.py
baml_agents/_agent_tools/_json_schema_to_baml_source/_json_to_model.py
baml_agents/_agent_tools/_json_schema_to_baml_source/_model.py
baml_agents/_agent_tools/_json_schema_to_baml_source/_model_to_baml_source.py
baml_agents/_agent_tools/_mcp_schema_to_type_builder/__init__.py
baml_agents/_agent_tools/_mcp_schema_to_type_builder/_abstract_json_schema_to_baml_converter.py
baml_agents/_agent_tools/_mcp_schema_to_type_builder/_baml_tool_prompt_config.py
baml_agents/_agent_tools/_mcp_schema_to_type_builder/_facade.py
baml_agents/_agent_tools/_mcp_schema_to_type_builder/_json_schema_to_baml_converter.py
baml_agents/_agent_tools/_mcp_schema_to_type_builder/_tool_to_baml_type.py
baml_agents/_agent_tools/_mcp_schema_to_type_builder/_type_builder_orchestrator.py
baml_agents/_agent_tools/_utils/__init__.py
baml_agents/_agent_tools/_utils/_baml_utils.py
baml_agents/_agent_tools/_utils/_snake_to_pascal.py
baml_agents/_baml_client_proxy/__init__.py
baml_agents/_baml_client_proxy/_baml_client_proxy.py
baml_agents/_baml_client_proxy/_hook_engine.py
baml_agents/_baml_client_proxy/_with_hooks.py
baml_agents/_baml_client_proxy/_hooks/__init__.py
baml_agents/_baml_client_proxy/_hooks/_base_hook.py
baml_agents/_baml_client_proxy/_hooks/_handle_llm_interaction_hook.py
baml_agents/_baml_client_proxy/_hooks/_on_after_call_success_hook.py
baml_agents/_baml_client_proxy/_hooks/_on_before_call_hook.py
baml_agents-0.46.1.dist-info/METADATA
baml_agents-0.46.1.dist-info/WHEEL
baml_agents-0.46.1.dist-info/entry_points.txt
baml_agents-0.46.1.dist-info/licenses/LICENSE
baml_agents-0.46.1.dist-info/RECORD
