Metadata-Version: 2.4
Name: baml-agents
Version: 0.46.1
Summary: Building Agents with LLM structured generation (BAML), MCP Tools, and 12-Factor Agents principles
License-File: LICENSE
Requires-Python: >=3.11
Requires-Dist: baml-py>=0.86.1
Requires-Dist: frozendict>=2.4.6
Requires-Dist: loguru>=0.7.3
Requires-Dist: pydantic>=2.11.3
Requires-Dist: requests>=2.32.3
